[
  {
    "day": "Tuesday",
    "strat_a": {
      "trades": 347,
      "wr": 51.5850144092219,
      "pf": 0.5912501930924305,
      "net": -17770.052695299706
    },
    "strat_b": {
      "trades": 71,
      "wr": 33.80281690140845,
      "pf": 0.3977744471883769,
      "net": -5138.6555620382505
    },
    "combined": {
      "trades": 418,
      "wr": 48.5645933014354,
      "pf": 0.5595066330979402,
      "net": -22908.708257337956
    }
  },
  {
    "day": "Wednesday",
    "strat_a": {
      "trades": 351,
      "wr": 53.84615384615385,
      "pf": 0.6365291204053085,
      "net": -16792.660317598395
    },
    "strat_b": {
      "trades": 46,
      "wr": 41.30434782608695,
      "pf": 0.5082018873225272,
      "net": -2321.2909492483027
    },
    "combined": {
      "trades": 397,
      "wr": 52.39294710327456,
      "pf": 0.6246340801536802,
      "net": -19113.951266846692
    }
  },
  {
    "day": "Thursday",
    "strat_a": {
      "trades": 352,
      "wr": 53.69318181818182,
      "pf": 0.5711702924367081,
      "net": -18519.211636116554
    },
    "strat_b": {
      "trades": 35,
      "wr": 34.285714285714285,
      "pf": 0.5769453496227932,
      "net": -1275.7519162113658
    },
    "combined": {
      "trades": 387,
      "wr": 51.93798449612403,
      "pf": 0.571547234227319,
      "net": -19794.963552327918
    }
  },
  {
    "day": "Friday",
    "strat_a": {
      "trades": 345,
      "wr": 61.15942028985507,
      "pf": 0.8333702088193161,
      "net": -7061.7114594696795
    },
    "strat_b": {
      "trades": 52,
      "wr": 36.53846153846153,
      "pf": 0.30367836529066616,
      "net": -4214.640407862354
    },
    "combined": {
      "trades": 397,
      "wr": 57.93450881612091,
      "pf": 0.7671732197118579,
      "net": -11276.351867332034
    }
  }
]